seli/__init__.py
seli/_env.py
seli/core/__init__.py
seli/core/_jit.py
seli/core/_module.py
seli/core/_property.py
seli/core/_registry.py
seli/core/_serialize.py
seli/core/_typecheck.py
seli/core/_utils.py
seli/net/__init__.py
seli/net/_attention.py
seli/net/_combine.py
seli/net/_einops.py
seli/net/_init.py
seli/net/_key.py
seli/net/_linear.py
seli/net/_norm.py
seli/net/_param.py
seli/net/_transform.py
seli/opt/__init__.py
seli/opt/_adagrad.py
seli/opt/_adam.py
seli/opt/_grad.py
seli/opt/_loss.py
seli/opt/_momentum.py
seli/opt/_nesterov.py
seli/opt/_opt.py
seli/opt/_rmsprop.py
seli/opt/_sgd.py
seli/opt/_utils.py
seli-0.1.2.dist-info/METADATA
seli-0.1.2.dist-info/WHEEL
seli-0.1.2.dist-info/top_level.txt
seli-0.1.2.dist-info/RECORD
