Metadata-Version: 2.4
Name: seli
Version: 0.1.2
Summary: A Python package called seli
Author-email: Paul Wollenhaupt <paul.wollenhaupt@gmail.com>
License: MIT
Project-URL: Homepage, https://github.com/paulwollenhaupt/seli
Project-URL: Bug Tracker, https://github.com/paulwollenhaupt/seli/issues
Classifier: Programming Language :: Python :: 3
Classifier: License :: OSI Approved :: MIT License
Classifier: Operating System :: OS Independent
Requires-Python: >=3.11
Requires-Dist: jax>=0.4.25
Requires-Dist: beartype>=0.20.0
Requires-Dist: jaxtyping>=0.2.38
Requires-Dist: einops>=0.8.1
Provides-Extra: dev
Requires-Dist: pytest>=7.0.0; extra == "dev"
Requires-Dist: pytest-cov>=4.0.0; extra == "dev"
Requires-Dist: black>=23.0.0; extra == "dev"
Requires-Dist: isort>=5.12.0; extra == "dev"
Requires-Dist: mypy>=1.0.0; extra == "dev"
Requires-Dist: ruff>=0.9.0; extra == "dev"
Requires-Dist: pre-commit>=4.0.0; extra == "dev"
Provides-Extra: docs
Requires-Dist: sphinx>=6.0.0; extra == "docs"
Requires-Dist: sphinx-rtd-theme>=1.2.0; extra == "docs"
Requires-Dist: myst-parser>=2.0.0; extra == "docs"
Requires-Dist: sphinx-book-theme>=1.0.0; extra == "docs"
Requires-Dist: sphinx-copybutton>=0.5.0; extra == "docs"
Requires-Dist: sphinx-toolbox>=3.0.0; extra == "docs"
Requires-Dist: sphinx-automodapi>=0.14.0; extra == "docs"
Requires-Dist: sphinx-favicon>=1.0.0; extra == "docs"
Provides-Extra: examples
Requires-Dist: matplotlib>=3.8.0; extra == "examples"
Requires-Dist: tqdm>=4.67.1; extra == "examples"
